ainotes/__init__.py
ainotes/decision/confidence.py
ainotes/decision/introduction.py
ainotes/foundations/calculus.py
ainotes/foundations/linear_algebra.py
ainotes/foundations/proba_stats.py
ainotes/foundations/programming.py
ainotes/ml/ann.py
ainotes/ml/challenges/cifar10.py
ainotes/ml/challenges/cifar10_solution.py
ainotes/ml/challenges/heart_disease.py
ainotes/ml/challenges/heart_disease_solution.py
ainotes/ml/classification.py
ainotes/ml/cnn.py
ainotes/ml/data.py
ainotes/ml/introduction.py
ainotes/ml/principles.py
ainotes/ml/regression.py
ainotes/ml/rl.py
ainotes/search/dijkstra_astar.py
ainotes/utils/plot.py
ainotes/utils/train.py
ainotes-1.0.1.dist-info/LICENSE
ainotes-1.0.1.dist-info/METADATA
ainotes-1.0.1.dist-info/WHEEL
ainotes-1.0.1.dist-info/RECORD
